{
    "data": {
        "deliveries": [
            {
                "id": "15005.1639.0",
                "event_log_entry_id": 533990,
                "event_type": "Shotgun_PublishedFile_New",
                "operation": "create",
                "user": {
                    "type": "ApiUser",
                    "id": 99
                },
                "entity": {
                    "type": "PublishedFile",
                    "id": 1113
                },
                "project": {
                    "type": "Project",
                    "id": 155
                },
                "meta": {
                    "type": "new_entity",
                    "entity_type": "PublishedFile",
                    "entity_id": 1113
                },
                "created_at": "2024-09-06 05:49:09.754923",
                "attribute_name": null,
                "session_uuid": null,
                "delivery_id": "8eb58499-59a1-41d1-98f5-c396637010a7"
            }
        ]
    },
    "timestamp": "2024-09-06T05:49:11Z"
}