{
    "data": {
        "deliveries": [
            {
                "id": "14670.1614.0",
                "event_log_entry_id": 533184,
                "event_type": "Shotgun_Version_New",
                "operation": "create",
                "user": {
                    "type": "ApiUser",
                    "id": 99
                },
                "entity": {
                    "type": "Version",
                    "id": 8888
                },
                "project": {
                    "type": "Project",
                    "id": 155
                },
                "meta": {
                    "type": "new_entity",
                    "entity_type": "Version",
                    "entity_id": 8888
                },
                "created_at": "2024-09-06 04:40:38.915209",
                "attribute_name": null,
                "session_uuid": null,
                "delivery_id": "0b82c0a4-3f3a-425e-adfc-f41aa5ea6bb5"
            }
        ]
    },
    "timestamp": "2024-09-06T04:40:41Z"
}